langerhans/__init__.py
langerhans/analysis.py
langerhans/data.py
langerhans/global_analysis.py
langerhans/network.py
langerhans-1.7.0.dist-info/METADATA
langerhans-1.7.0.dist-info/WHEEL
langerhans-1.7.0.dist-info/top_level.txt
langerhans-1.7.0.dist-info/RECORD
