Metadata-Version: 2.1
Name: langerhans
Version: 1.7.0
Summary: Analyzer for the calcium signals of Islets of Langerhans.
Home-page: https://github.com/janzmazek/langerhans
Author: Jan Zmazek
License: MIT License
Platform: UNKNOWN
Requires-Python: >3.6.0
Requires-Dist: numpy
Requires-Dist: scipy
Requires-Dist: matplotlib
Requires-Dist: pandas
Requires-Dist: networkx
Requires-Dist: pyyaml
Requires-Dist: python-louvain
